kerascv/__init__.py
kerascv/model_provider.py
kerascv/models/__init__.py
kerascv/models/alexnet.py
kerascv/models/common.py
kerascv/models/darknet.py
kerascv/models/darknet53.py
kerascv/models/densenet.py
kerascv/models/efficientnet.py
kerascv/models/igcv3.py
kerascv/models/menet.py
kerascv/models/mnasnet.py
kerascv/models/mnasnet_old.py
kerascv/models/mobilenet.py
kerascv/models/mobilenetv2.py
kerascv/models/mobilenetv3.py
kerascv/models/model_store.py
kerascv/models/preresnet.py
kerascv/models/resnet.py
kerascv/models/resnext.py
kerascv/models/senet.py
kerascv/models/sepreresnet.py
kerascv/models/seresnet.py
kerascv/models/seresnext.py
kerascv/models/shufflenet.py
kerascv/models/shufflenetv2.py
kerascv/models/shufflenetv2b.py
kerascv/models/squeezenet.py
kerascv/models/squeezenext.py
kerascv/models/vgg.py
kerascv/models/zfnet.py
kerascv-0.0.40.dist-info/LICENSE.txt
kerascv-0.0.40.dist-info/METADATA
kerascv-0.0.40.dist-info/WHEEL
kerascv-0.0.40.dist-info/top_level.txt
kerascv-0.0.40.dist-info/RECORD
