Metadata-Version: 2.1
Name: kerascv
Version: 0.0.40
Summary: Image classification models for Keras
Home-page: https://github.com/osmr/imgclsmob
Author: Oleg Sémery
Author-email: osemery@gmail.com
License: MIT
Keywords: machine-learning deep-learning neuralnetwork image-classification keras keras-mxnet imagenet vgg resnet resnext senet densenet darknet squeezenet squeezenext shufflenet menet mobilenent igcv3 mnasnet efficientnet
Platform: UNKNOWN
Classifier: Development Status :: 3 - Alpha
Classifier: Intended Audience :: Science/Research
Classifier: License :: OSI Approved :: MIT License
Classifier: Operating System :: OS Independent
Classifier: Programming Language :: Python
Classifier: Topic :: Scientific/Engineering :: Image Recognition
Requires-Dist: h5py
